SinaTools/nlptools/__init__.py
SinaTools/nlptools/nlptools.py
nlptools/VERSION
nlptools/__init__.py
nlptools/cli.py
nlptools/environment.yml
nlptools/install_env.py
nlptools/nlptools.py
nlptools/CLI/DataDownload/download_files.py
nlptools/CLI/arabiner/bin/infer.py
nlptools/CLI/arabiner/bin/infer2.py
nlptools/CLI/morphology/ALMA_multi_word.py
nlptools/CLI/morphology/morph_analyzer.py
nlptools/CLI/salma/salma_tools.py
nlptools/CLI/utils/__init__.py
nlptools/CLI/utils/arStrip.py
nlptools/CLI/utils/corpus_tokenizer.py
nlptools/CLI/utils/corpus_tokenizer_keep_columns.py
nlptools/CLI/utils/implication.py
nlptools/CLI/utils/jaccard.py
nlptools/CLI/utils/jaccard_intersection.py
nlptools/CLI/utils/jaccard_similarity.py
nlptools/CLI/utils/jaccard_union.py
nlptools/CLI/utils/latin_remove.py
nlptools/CLI/utils/remove_Punc.py
nlptools/CLI/utils/sentence_tokenizer.py
nlptools/CLI/utils/text_transliteration.py
nlptools/DataDownload/__init__.py
nlptools/DataDownload/downloader.py
nlptools/arabert/__init__.py
nlptools/arabert/preprocess.py
nlptools/arabert/arabert/__init__.py
nlptools/arabert/arabert/create_classification_data.py
nlptools/arabert/arabert/create_pretraining_data.py
nlptools/arabert/arabert/extract_features.py
nlptools/arabert/arabert/lamb_optimizer.py
nlptools/arabert/arabert/modeling.py
nlptools/arabert/arabert/optimization.py
nlptools/arabert/arabert/run_classifier.py
nlptools/arabert/arabert/run_pretraining.py
nlptools/arabert/arabert/run_squad.py
nlptools/arabert/arabert/tokenization.py
nlptools/arabert/araelectra/__init__.py
nlptools/arabert/araelectra/build_openwebtext_pretraining_dataset.py
nlptools/arabert/araelectra/build_pretraining_dataset.py
nlptools/arabert/araelectra/build_pretraining_dataset_single_file.py
nlptools/arabert/araelectra/configure_finetuning.py
nlptools/arabert/araelectra/configure_pretraining.py
nlptools/arabert/araelectra/flops_computation.py
nlptools/arabert/araelectra/run_finetuning.py
nlptools/arabert/araelectra/run_pretraining.py
nlptooltest-0.9.119.dist-info/AUTHORS.rst
nlptooltest-0.9.119.dist-info/LICENSE
nlptooltest-0.9.119.dist-info/METADATA
nlptooltest-0.9.119.dist-info/WHEEL
nlptooltest-0.9.119.dist-info/entry_points.txt
nlptooltest-0.9.119.dist-info/top_level.txt
nlptooltest-0.9.119.dist-info/RECORD
