Metadata-Version: 2.1
Name: nlptooltest
Version: 0.9.119
Summary: UNKNOWN
Home-page: https://github.com/SinaLab/nlptools
Author: UNKNOWN
Author-email: UNKNOWN
License: MIT license
Keywords: nlptools
Platform: UNKNOWN
Requires-Dist: six
Requires-Dist: farasapy
Requires-Dist: tqdm
Requires-Dist: requests
Requires-Dist: regex
Requires-Dist: pathlib
Requires-Dist: torch (==1.13.0)
Requires-Dist: transformers (==4.24.0)
Requires-Dist: torchtext (==0.14.0)
Requires-Dist: torchvision (==0.14.0)
Requires-Dist: seqeval (==1.2.2)
Requires-Dist: natsort (==7.1.1)
